{
  "headers": {
    "x-amz-cf-pop": "SEA73-P3",
    "age": "577637",
    "content-security-policy": "default-src 'none'; style-src 'unsafe-inline'; sandbox",
    "content-length": "1897",
    "cross-origin-opener-policy": "same-origin",
    "x-amz-server-side-encryption": "AES256",
    "last-modified": "Thu, 24 Aug 2023 15:44:13 GMT",
    "vary": "Accept-Encoding, Origin",
    "date": "Mon, 28 Aug 2023 21:57:09 GMT",
    "server-timing": "fetchSource;dur=830",
    "accept-ranges": "bytes",
    "content-type": "application/typescript; charset=utf-8",
    "x-frame-options": "DENY",
    "cache-control": "public, max-age=31536000, immutable",
    "cross-origin-embedder-policy": "same-origin",
    "x-amz-replication-status": "COMPLETED",
    "x-amz-version-id": "kcnD_Au8cpjTUasIBEe1XA8c0r1axO2q",
    "access-control-allow-origin": "*",
    "etag": "\"dac81729342c8cdad4948e94ed77e3d5\"",
    "via": "http/2 edgeproxy-h",
    "strict-transport-security": "max-age=63072000; includeSubDomains; preload",
    "referrer-policy": "strict-origin-when-cross-origin",
    "x-cache": "Hit from cloudfront",
    "server": "deno/gcp-us-west1",
    "x-content-type-options": "nosniff",
    "cross-origin-resource-policy": "same-origin",
    "x-amz-cf-id": "JIx25ufMJqq0FqxQOc1tnPF34pdQofwg7bqCQG-dBNRFpc5yLUOZMg=="
  },
  "url": "https://deno.land/std@0.200.0/streams/read_all.ts",
  "now": {
    "secs_since_epoch": 1693837466,
    "nanos_since_epoch": 643557039
  }
}