{
  "headers": {
    "cache-control": "public, max-age=31536000, immutable",
    "server": "deno/gcp-us-west1",
    "accept-ranges": "bytes",
    "cross-origin-resource-policy": "same-origin",
    "strict-transport-security": "max-age=63072000; includeSubDomains; preload",
    "x-amz-cf-id": "IappKEnQOz9Rr_t69RjPtmOCyprKXexqCAA_swCo82eCJivtoKTBdQ==",
    "x-frame-options": "DENY",
    "date": "Wed, 30 Aug 2023 03:34:40 GMT",
    "via": "http/2 edgeproxy-h",
    "x-amz-server-side-encryption": "AES256",
    "content-type": "application/typescript; charset=utf-8",
    "x-amz-replication-status": "COMPLETED",
    "x-cache": "Hit from cloudfront",
    "vary": "Accept-Encoding, Origin",
    "referrer-policy": "strict-origin-when-cross-origin",
    "content-length": "4968",
    "content-security-policy": "default-src 'none'; style-src 'unsafe-inline'; sandbox",
    "last-modified": "Wed, 30 Aug 2023 03:31:53 GMT",
    "x-amz-cf-pop": "SEA73-P3",
    "access-control-allow-origin": "*",
    "x-content-type-options": "nosniff",
    "etag": "\"91c724f2ba06d8b8d43055bb9eeaa5cb\"",
    "x-amz-version-id": "5xcVLtf6kMOEf8JJm4aAcSa2lSVMrbCo",
    "server-timing": "fetchSource;dur=616",
    "cross-origin-embedder-policy": "same-origin",
    "cross-origin-opener-policy": "same-origin",
    "age": "470982"
  },
  "url": "https://deno.land/x/oak@v12.6.1/structured_clone.ts",
  "now": {
    "secs_since_epoch": 1693837462,
    "nanos_since_epoch": 446074900
  }
}