{
  "headers": {
    "content-length": "684",
    "x-amz-cf-pop": "SEA73-P3",
    "date": "Mon, 04 Sep 2023 14:24:25 GMT",
    "x-content-type-options": "nosniff",
    "content-security-policy": "default-src 'none'; style-src 'unsafe-inline'; sandbox",
    "last-modified": "Wed, 02 Aug 2023 11:26:36 GMT",
    "content-type": "application/typescript; charset=utf-8",
    "cache-control": "public, max-age=31536000, immutable",
    "server": "deno/gcp-us-west1",
    "vary": "Accept-Encoding, Origin",
    "cross-origin-embedder-policy": "same-origin",
    "strict-transport-security": "max-age=63072000; includeSubDomains; preload",
    "x-cache": "Miss from cloudfront",
    "cross-origin-opener-policy": "same-origin",
    "x-amz-cf-id": "Ys0phBAkEVDD9--GCNWIXXsIivWe9ibJ8lLEf_309g6kZwkZDwAYbQ==",
    "x-amz-replication-status": "COMPLETED",
    "x-amz-server-side-encryption": "AES256",
    "server-timing": "fetchSource;dur=348",
    "access-control-allow-origin": "*",
    "accept-ranges": "bytes",
    "x-amz-version-id": "7A65QD42XprM6YafHXCOjw7I7Wo6zGv.",
    "etag": "\"b951c18b58de8b15714ae85fed6fe275\"",
    "x-frame-options": "DENY",
    "cross-origin-resource-policy": "same-origin",
    "via": "http/2 edgeproxy-h",
    "referrer-policy": "strict-origin-when-cross-origin"
  },
  "url": "https://deno.land/x/harmony@v2.9.0/deps.ts",
  "now": {
    "secs_since_epoch": 1693837464,
    "nanos_since_epoch": 972706143
  }
}